cherryblossom/.key
cherryblossom/Analyzer.py
cherryblossom/Blossom.py
cherryblossom/Channels.py
cherryblossom/Chat.py
cherryblossom/DB.py
cherryblossom/Data.py
cherryblossom/Functions.py
cherryblossom/GPTModel.py
cherryblossom/Index.py
cherryblossom/Plots.py
cherryblossom/Timezone.py
cherryblossom/__init__.py
cherryblossom/get_file.py
cherryblossom/imports.py
cherryblossom/key.py
cherryblossom/main.py
cherryblossom-0.1.6.dist-info/.ipynb_checkpoints/SOURCES-checkpoint.txt
cherryblossom-0.1.6.dist-info/.ipynb_checkpoints/dependency_links-checkpoint.txt
cherryblossom-0.1.6.dist-info/.ipynb_checkpoints/requires-checkpoint.txt
cherryblossom-0.1.6.dist-info/.ipynb_checkpoints/top_level-checkpoint.txt
cherryblossom-0.1.6.dist-info/METADATA
cherryblossom-0.1.6.dist-info/WHEEL
cherryblossom-0.1.6.dist-info/top_level.txt
cherryblossom-0.1.6.dist-info/RECORD
