Metadata-Version: 2.1
Name: cherryblossom
Version: 0.1.6
Summary: CherryBlossom: an API for Nosedive AI
Author-email: Arjun Naik <arjunsatishnaik@gmail.com>
Project-URL: Homepage, https://github.com/Aleph-Null-123/nosedive
Classifier: Programming Language :: Python :: 3
Classifier: Operating System :: OS Independent
Requires-Python: >=3.7
Requires-Dist: setuptools
Requires-Dist: pandas
Requires-Dist: matplotlib
Requires-Dist: numpy
Requires-Dist: datetime
Requires-Dist: pytz
Requires-Dist: tzlocal
Requires-Dist: emoji
Requires-Dist: openai
Requires-Dist: paramiko
Requires-Dist: scp
Requires-Dist: uuid
